valoria/__init__.py
valoria/chmod.py
valoria/clean.py
valoria/cli.py
valoria/dependencies.py
valoria/license.py
valoria/perm.py
valoria/structure.py
valoria/tmp.py
valoria-0.1.0.dist-info/METADATA
valoria-0.1.0.dist-info/WHEEL
valoria-0.1.0.dist-info/entry_points.txt
valoria-0.1.0.dist-info/top_level.txt
valoria-0.1.0.dist-info/RECORD
