Metadata-Version: 2.4
Name: valoria
Version: 0.1.0
Summary: Outils pour gérer fichiers: structure, tmp, permissions, nettoyage, dépendances, chmod
Author: GameurDev
License: MIT
Requires-Python: >=3.8
